{
	"use_common_dialog": false,
	"addin_window": {
		"normal" : {
			"left": 100, "top": 200,
			"right": 300, "bottom": 400
		},
		"show_cmd": 0
	},
	"filer": [
		{
			"filer_window": {
				"normal" : {
					"left": 300, "top": 300,
					"right": 1300, "bottom": 800
				},
				"show_cmd": 0
			},
			"name": "素材1"
		},
		{
			"filer_window": {
				"normal" : {
					"left": 400, "top": 400,
					"right": 1400, "bottom": 900
				},
				"show_cmd": 0
			},
			"name": "素材2"
		},
		{
			"filer_window": {
				"normal" : {
					"left": 500, "top": 500,
					"right": 1500, "bottom": 1000
				},
				"show_cmd": 0
			},
			"name": "素材3"
		}
	]
}